LICENSE
README.md
setup.py
advanced_geometry_utils.egg-info/PKG-INFO
advanced_geometry_utils.egg-info/SOURCES.txt
advanced_geometry_utils.egg-info/dependency_links.txt
advanced_geometry_utils.egg-info/top_level.txt
geometry_utils/__init__.py
geometry_utils/maths_utility.py
geometry_utils/path_field_interpreter.py
geometry_utils/three_d/__init__.py
geometry_utils/three_d/axis_aligned_box3.py
geometry_utils/three_d/edge3.py
geometry_utils/three_d/matrix4.py
geometry_utils/three_d/path3.py
geometry_utils/three_d/point3.py
geometry_utils/three_d/vector3.py
geometry_utils/two_d/__init__.py
geometry_utils/two_d/axis_aligned_box2.py
geometry_utils/two_d/edge2.py
geometry_utils/two_d/ellipse.py
geometry_utils/two_d/intersection.py
geometry_utils/two_d/matrix3.py
geometry_utils/two_d/path2.py
geometry_utils/two_d/point2.py
geometry_utils/two_d/vector2.py